{"__type__":"sp.SkeletonData","_name":"leaflet","skeletonJsonStr":"{\n\"skeleton\": { \"hash\": \"LN+BRHYhEJJDDQu9XEu9lGJJwF4\", \"spine\": \"3.6.52\", \"width\": 87, \"height\": 56.4, \"images\": \"\" },\n\"bones\": [\n\t{ \"name\": \"root\" },\n\t{ \"name\": \"normal/leaflet\", \"parent\": \"root\" }\n],\n\"slots\": [\n\t{ \"name\": \"normal/leaflet\", \"bone\": \"normal/leaflet\", \"attachment\": \"leaflet\" },\n\t{ \"name\": \"normal/leaflet3\", \"bone\": \"normal/leaflet\", \"attachment\": \"leaflet\" }\n],\n\"skins\": {\n\t\"default\": {},\n\t\"normal\": {\n\t\t\"normal/leaflet\": {\n\t\t\t\"leaflet\": {\n\t\t\t\t\"name\": \"normal/leaflet\",\n\t\t\t\t\"type\": \"mesh\",\n\t\t\t\t\"uvs\": [ 1, 1, 0, 1, 0, 0, 1, 0 ],\n\t\t\t\t\"triangles\": [ 1, 2, 3, 1, 3, 0 ],\n\t\t\t\t\"vertices\": [ 44.31, -26.02, -42.69, -26.02, -42.69, 29.98, 44.31, 29.98 ],\n\t\t\t\t\"hull\": 4,\n\t\t\t\t\"edges\": [ 0, 2, 2, 4, 4, 6, 0, 6 ],\n\t\t\t\t\"width\": 87,\n\t\t\t\t\"height\": 56\n\t\t\t}\n\t\t},\n\t\t\"normal/leaflet3\": {\n\t\t\t\"leaflet\": {\n\t\t\t\t\"name\": \"normal/leaflet\",\n\t\t\t\t\"type\": \"mesh\",\n\t\t\t\t\"uvs\": [ 1, 1, 0, 1, 0, 0, 1, 0 ],\n\t\t\t\t\"triangles\": [ 1, 2, 3, 1, 3, 0 ],\n\t\t\t\t\"vertices\": [ -42.69, -26.42, 44.31, -26.42, 44.31, 29.58, -42.69, 29.58 ],\n\t\t\t\t\"hull\": 4,\n\t\t\t\t\"edges\": [ 0, 2, 2, 4, 4, 6, 0, 6 ],\n\t\t\t\t\"width\": 87,\n\t\t\t\t\"height\": 56\n\t\t\t}\n\t\t}\n\t}\n},\n\"animations\": {\n\t\"l1\": {\n\t\t\"slots\": {\n\t\t\t\"normal/leaflet\": {\n\t\t\t\t\"attachment\": [\n\t\t\t\t\t{ \"time\": 0, \"name\": \"leaflet\" },\n\t\t\t\t\t{ \"time\": 0.4333, \"name\": \"leaflet\" },\n\t\t\t\t\t{ \"time\": 0.6333, \"name\": \"leaflet\" },\n\t\t\t\t\t{ \"time\": 0.6667, \"name\": null },\n\t\t\t\t\t{ \"time\": 1, \"name\": null },\n\t\t\t\t\t{ \"time\": 1.3333, \"name\": null },\n\t\t\t\t\t{ \"time\": 1.8, \"name\": null },\n\t\t\t\t\t{ \"time\": 2, \"name\": \"leaflet\" },\n\t\t\t\t\t{ \"time\": 2.3333, \"name\": \"leaflet\" },\n\t\t\t\t\t{ \"time\": 2.6667, \"name\": \"leaflet\" }\n\t\t\t\t]\n\t\t\t},\n\t\t\t\"normal/leaflet3\": {\n\t\t\t\t\"attachment\": [\n\t\t\t\t\t{ \"time\": 0, \"name\": null },\n\t\t\t\t\t{ \"time\": 0.4333, \"name\": null },\n\t\t\t\t\t{ \"time\": 0.6333, \"name\": null },\n\t\t\t\t\t{ \"time\": 0.6667, \"name\": \"leaflet\" },\n\t\t\t\t\t{ \"time\": 1, \"name\": \"leaflet\" },\n\t\t\t\t\t{ \"time\": 1.3333, \"name\": \"leaflet\" },\n\t\t\t\t\t{ \"time\": 1.8, \"name\": \"leaflet\" },\n\t\t\t\t\t{ \"time\": 2, \"name\": null },\n\t\t\t\t\t{ \"time\": 2.3333, \"name\": null },\n\t\t\t\t\t{ \"time\": 2.6667, \"name\": null }\n\t\t\t\t]\n\t\t\t}\n\t\t},\n\t\t\"bones\": {\n\t\t\t\"root\": {\n\t\t\t\t\"rotate\": [\n\t\t\t\t\t{ \"time\": 0, \"angle\": 0, \"curve\": \"stepped\" },\n\t\t\t\t\t{ \"time\": 1.3333, \"angle\": 0, \"curve\": \"stepped\" },\n\t\t\t\t\t{ \"time\": 2.6667, \"angle\": 0 }\n\t\t\t\t],\n\t\t\t\t\"translate\": [\n\t\t\t\t\t{ \"time\": 0, \"x\": 0, \"y\": 0, \"curve\": \"stepped\" },\n\t\t\t\t\t{ \"time\": 1.3333, \"x\": 0, \"y\": 0, \"curve\": \"stepped\" },\n\t\t\t\t\t{ \"time\": 2.6667, \"x\": 0, \"y\": 0 }\n\t\t\t\t],\n\t\t\t\t\"scale\": [\n\t\t\t\t\t{ \"time\": 0, \"x\": 1, \"y\": 1, \"curve\": \"stepped\" },\n\t\t\t\t\t{ \"time\": 1.3333, \"x\": 1, \"y\": 1, \"curve\": \"stepped\" },\n\t\t\t\t\t{ \"time\": 2.6667, \"x\": 1, \"y\": 1 }\n\t\t\t\t]\n\t\t\t},\n\t\t\t\"normal/leaflet\": {\n\t\t\t\t\"rotate\": [\n\t\t\t\t\t{ \"time\": 0, \"angle\": 0 },\n\t\t\t\t\t{ \"time\": 0.6667, \"angle\": -90 },\n\t\t\t\t\t{ \"time\": 1.3333, \"angle\": 180 },\n\t\t\t\t\t{ \"time\": 2.6667, \"angle\": 0 }\n\t\t\t\t],\n\t\t\t\t\"translate\": [\n\t\t\t\t\t{ \"time\": 0, \"x\": 0, \"y\": 0, \"curve\": \"stepped\" },\n\t\t\t\t\t{ \"time\": 1.3333, \"x\": 0, \"y\": 0, \"curve\": \"stepped\" },\n\t\t\t\t\t{ \"time\": 2.6667, \"x\": 0, \"y\": 0 }\n\t\t\t\t],\n\t\t\t\t\"scale\": [\n\t\t\t\t\t{ \"time\": 0, \"x\": 1, \"y\": 1, \"curve\": \"stepped\" },\n\t\t\t\t\t{ \"time\": 1.3333, \"x\": 1, \"y\": 1, \"curve\": \"stepped\" },\n\t\t\t\t\t{ \"time\": 2.6667, \"x\": 1, \"y\": 1 }\n\t\t\t\t],\n\t\t\t\t\"shear\": [\n\t\t\t\t\t{ \"time\": 0, \"x\": 0, \"y\": 0, \"curve\": \"stepped\" },\n\t\t\t\t\t{ \"time\": 1.3333, \"x\": 0, \"y\": 0, \"curve\": \"stepped\" },\n\t\t\t\t\t{ \"time\": 2.6667, \"x\": 0, \"y\": 0 }\n\t\t\t\t]\n\t\t\t}\n\t\t},\n\t\t\"deform\": {\n\t\t\t\"normal\": {\n\t\t\t\t\"normal/leaflet\": {\n\t\t\t\t\t\"leaflet\": [\n\t\t\t\t\t\t{ \"time\": 0 },\n\t\t\t\t\t\t{\n\t\t\t\t\t\t\t\"time\": 0.4333,\n\t\t\t\t\t\t\t\"offset\": 1,\n\t\t\t\t\t\t\t\"vertices\": [ 22.57752, 0, 22.57752, 0, -22.57752, 0, -22.57752 ]\n\t\t\t\t\t\t},\n\t\t\t\t\t\t{\n\t\t\t\t\t\t\t\"time\": 0.6667,\n\t\t\t\t\t\t\t\"offset\": 1,\n\t\t\t\t\t\t\t\"vertices\": [ 27.52428, 0, 27.52428, 0, -27.52428, 0, -27.52428 ]\n\t\t\t\t\t\t},\n\t\t\t\t\t\t{ \"time\": 1, \"curve\": \"stepped\" },\n\t\t\t\t\t\t{ \"time\": 1.3333 },\n\t\t\t\t\t\t{\n\t\t\t\t\t\t\t\"time\": 1.8,\n\t\t\t\t\t\t\t\"offset\": 1,\n\t\t\t\t\t\t\t\"vertices\": [ 23.71909, 0, 23.71909, 0, -23.71909, 0, -23.71909 ]\n\t\t\t\t\t\t},\n\t\t\t\t\t\t{\n\t\t\t\t\t\t\t\"time\": 2,\n\t\t\t\t\t\t\t\"offset\": 1,\n\t\t\t\t\t\t\t\"vertices\": [ 27.25158, 0, 27.25158, 0, -27.25161, 0, -27.25161 ]\n\t\t\t\t\t\t},\n\t\t\t\t\t\t{\n\t\t\t\t\t\t\t\"time\": 2.3333,\n\t\t\t\t\t\t\t\"offset\": 1,\n\t\t\t\t\t\t\t\"vertices\": [ 19.90234, 0, 19.90234, 0, -19.90234, 0, -19.90234 ]\n\t\t\t\t\t\t},\n\t\t\t\t\t\t{ \"time\": 2.6667 }\n\t\t\t\t\t]\n\t\t\t\t},\n\t\t\t\t\"normal/leaflet3\": {\n\t\t\t\t\t\"leaflet\": [\n\t\t\t\t\t\t{ \"time\": 0 },\n\t\t\t\t\t\t{\n\t\t\t\t\t\t\t\"time\": 0.4333,\n\t\t\t\t\t\t\t\"offset\": 1,\n\t\t\t\t\t\t\t\"vertices\": [ 25.62167, 0, 25.62167, 0, -25.6217, 0, -25.6217 ]\n\t\t\t\t\t\t},\n\t\t\t\t\t\t{\n\t\t\t\t\t\t\t\"time\": 0.6333,\n\t\t\t\t\t\t\t\"offset\": 1,\n\t\t\t\t\t\t\t\"vertices\": [ 27.20717, 0, 27.20717, 0, -27.2072, 0, -27.2072 ]\n\t\t\t\t\t\t},\n\t\t\t\t\t\t{\n\t\t\t\t\t\t\t\"time\": 0.6667,\n\t\t\t\t\t\t\t\"offset\": 1,\n\t\t\t\t\t\t\t\"vertices\": [ 27.52427, 0, 27.52427, 0, -27.5243, 0, -27.5243 ]\n\t\t\t\t\t\t},\n\t\t\t\t\t\t{\n\t\t\t\t\t\t\t\"time\": 1,\n\t\t\t\t\t\t\t\"offset\": 1,\n\t\t\t\t\t\t\t\"vertices\": [ 15.58978, 0, 15.58978, -1.0E-5, -15.58978, -1.0E-5, -15.58978 ]\n\t\t\t\t\t\t},\n\t\t\t\t\t\t{ \"time\": 1.3333 },\n\t\t\t\t\t\t{\n\t\t\t\t\t\t\t\"time\": 1.8,\n\t\t\t\t\t\t\t\"offset\": 1,\n\t\t\t\t\t\t\t\"vertices\": [ 14.27921, 1.0E-5, 14.27921, 0, -14.27916, 0, -14.27916 ]\n\t\t\t\t\t\t},\n\t\t\t\t\t\t{\n\t\t\t\t\t\t\t\"time\": 2,\n\t\t\t\t\t\t\t\"offset\": 1,\n\t\t\t\t\t\t\t\"vertices\": [ 27.57078, 0, 27.57078, 0, -27.5708, 0, -27.5708 ]\n\t\t\t\t\t\t},\n\t\t\t\t\t\t{\n\t\t\t\t\t\t\t\"time\": 2.3333,\n\t\t\t\t\t\t\t\"offset\": 1,\n\t\t\t\t\t\t\t\"vertices\": [ 37.55733, 0, 37.55733, 0, -37.55732, 0, -37.55732 ]\n\t\t\t\t\t\t},\n\t\t\t\t\t\t{ \"time\": 2.6667 }\n\t\t\t\t\t]\n\t\t\t\t}\n\t\t\t}\n\t\t}\n\t},\n\t\"l2\": {\n\t\t\"slots\": {\n\t\t\t\"normal/leaflet\": {\n\t\t\t\t\"attachment\": [\n\t\t\t\t\t{ \"time\": 0, \"name\": \"leaflet\" },\n\t\t\t\t\t{ \"time\": 0.4333, \"name\": \"leaflet\" },\n\t\t\t\t\t{ \"time\": 0.6333, \"name\": \"leaflet\" },\n\t\t\t\t\t{ \"time\": 0.6667, \"name\": null },\n\t\t\t\t\t{ \"time\": 1, \"name\": null },\n\t\t\t\t\t{ \"time\": 1.3333, \"name\": null },\n\t\t\t\t\t{ \"time\": 1.7667, \"name\": null },\n\t\t\t\t\t{ \"time\": 2, \"name\": \"leaflet\" },\n\t\t\t\t\t{ \"time\": 2.3333, \"name\": \"leaflet\" },\n\t\t\t\t\t{ \"time\": 2.6667, \"name\": \"leaflet\" }\n\t\t\t\t]\n\t\t\t},\n\t\t\t\"normal/leaflet3\": {\n\t\t\t\t\"attachment\": [\n\t\t\t\t\t{ \"time\": 0, \"name\": null },\n\t\t\t\t\t{ \"time\": 0.4333, \"name\": null },\n\t\t\t\t\t{ \"time\": 0.6333, \"name\": null },\n\t\t\t\t\t{ \"time\": 0.6667, \"name\": \"leaflet\" },\n\t\t\t\t\t{ \"time\": 1, \"name\": \"leaflet\" },\n\t\t\t\t\t{ \"time\": 1.3333, \"name\": \"leaflet\" },\n\t\t\t\t\t{ \"time\": 1.7667, \"name\": \"leaflet\" },\n\t\t\t\t\t{ \"time\": 2, \"name\": null },\n\t\t\t\t\t{ \"time\": 2.3333, \"name\": null },\n\t\t\t\t\t{ \"time\": 2.6667, \"name\": null }\n\t\t\t\t]\n\t\t\t}\n\t\t},\n\t\t\"bones\": {\n\t\t\t\"root\": {\n\t\t\t\t\"rotate\": [\n\t\t\t\t\t{ \"time\": 0, \"angle\": 0, \"curve\": \"stepped\" },\n\t\t\t\t\t{ \"time\": 1.3333, \"angle\": 0, \"curve\": \"stepped\" },\n\t\t\t\t\t{ \"time\": 2.6667, \"angle\": 0 }\n\t\t\t\t],\n\t\t\t\t\"translate\": [\n\t\t\t\t\t{ \"time\": 0, \"x\": 0, \"y\": 0, \"curve\": \"stepped\" },\n\t\t\t\t\t{ \"time\": 1.3333, \"x\": 0, \"y\": 0, \"curve\": \"stepped\" },\n\t\t\t\t\t{ \"time\": 2.6667, \"x\": 0, \"y\": 0 }\n\t\t\t\t],\n\t\t\t\t\"scale\": [\n\t\t\t\t\t{ \"time\": 0, \"x\": 1, \"y\": 1, \"curve\": \"stepped\" },\n\t\t\t\t\t{ \"time\": 1.3333, \"x\": 1, \"y\": 1, \"curve\": \"stepped\" },\n\t\t\t\t\t{ \"time\": 2.6667, \"x\": 1, \"y\": 1 }\n\t\t\t\t]\n\t\t\t},\n\t\t\t\"normal/leaflet\": {\n\t\t\t\t\"rotate\": [\n\t\t\t\t\t{ \"time\": 0, \"angle\": -90 },\n\t\t\t\t\t{ \"time\": 0.6667, \"angle\": 180 },\n\t\t\t\t\t{ \"time\": 1.3333, \"angle\": 90 },\n\t\t\t\t\t{ \"time\": 2.6667, \"angle\": -90 }\n\t\t\t\t],\n\t\t\t\t\"translate\": [\n\t\t\t\t\t{ \"time\": 0, \"x\": 0, \"y\": 0, \"curve\": \"stepped\" },\n\t\t\t\t\t{ \"time\": 1.3333, \"x\": 0, \"y\": 0, \"curve\": \"stepped\" },\n\t\t\t\t\t{ \"time\": 2.6667, \"x\": 0, \"y\": 0 }\n\t\t\t\t],\n\t\t\t\t\"scale\": [\n\t\t\t\t\t{ \"time\": 0, \"x\": 1, \"y\": 1, \"curve\": \"stepped\" },\n\t\t\t\t\t{ \"time\": 1.3333, \"x\": 1, \"y\": 1, \"curve\": \"stepped\" },\n\t\t\t\t\t{ \"time\": 2.6667, \"x\": 1, \"y\": 1 }\n\t\t\t\t],\n\t\t\t\t\"shear\": [\n\t\t\t\t\t{ \"time\": 0, \"x\": 0, \"y\": 0, \"curve\": \"stepped\" },\n\t\t\t\t\t{ \"time\": 1.3333, \"x\": 0, \"y\": 0, \"curve\": \"stepped\" },\n\t\t\t\t\t{ \"time\": 2.6667, \"x\": 0, \"y\": 0 }\n\t\t\t\t]\n\t\t\t}\n\t\t},\n\t\t\"deform\": {\n\t\t\t\"normal\": {\n\t\t\t\t\"normal/leaflet\": {\n\t\t\t\t\t\"leaflet\": [\n\t\t\t\t\t\t{ \"time\": 0 },\n\t\t\t\t\t\t{\n\t\t\t\t\t\t\t\"time\": 0.4333,\n\t\t\t\t\t\t\t\"offset\": 1,\n\t\t\t\t\t\t\t\"vertices\": [ 22.57752, 0, 22.57752, 0, -22.57752, 0, -22.57752 ]\n\t\t\t\t\t\t},\n\t\t\t\t\t\t{\n\t\t\t\t\t\t\t\"time\": 0.6667,\n\t\t\t\t\t\t\t\"offset\": 1,\n\t\t\t\t\t\t\t\"vertices\": [ 27.52428, 0, 27.52428, 0, -27.52428, 0, -27.52428 ]\n\t\t\t\t\t\t},\n\t\t\t\t\t\t{ \"time\": 1, \"curve\": \"stepped\" },\n\t\t\t\t\t\t{ \"time\": 1.3333 },\n\t\t\t\t\t\t{\n\t\t\t\t\t\t\t\"time\": 1.7667,\n\t\t\t\t\t\t\t\"offset\": 1,\n\t\t\t\t\t\t\t\"vertices\": [ 23.71909, 0, 23.71909, 0, -23.71909, 0, -23.71909 ]\n\t\t\t\t\t\t},\n\t\t\t\t\t\t{\n\t\t\t\t\t\t\t\"time\": 2,\n\t\t\t\t\t\t\t\"offset\": 1,\n\t\t\t\t\t\t\t\"vertices\": [ 27.25158, 0, 27.25158, 0, -27.25161, 0, -27.25161 ]\n\t\t\t\t\t\t},\n\t\t\t\t\t\t{\n\t\t\t\t\t\t\t\"time\": 2.3333,\n\t\t\t\t\t\t\t\"offset\": 1,\n\t\t\t\t\t\t\t\"vertices\": [ 19.90234, 0, 19.90234, 0, -19.90234, 0, -19.90234 ]\n\t\t\t\t\t\t},\n\t\t\t\t\t\t{ \"time\": 2.6667 }\n\t\t\t\t\t]\n\t\t\t\t},\n\t\t\t\t\"normal/leaflet3\": {\n\t\t\t\t\t\"leaflet\": [\n\t\t\t\t\t\t{ \"time\": 0 },\n\t\t\t\t\t\t{\n\t\t\t\t\t\t\t\"time\": 0.4333,\n\t\t\t\t\t\t\t\"offset\": 1,\n\t\t\t\t\t\t\t\"vertices\": [ 25.62167, 0, 25.62167, 0, -25.6217, 0, -25.6217 ]\n\t\t\t\t\t\t},\n\t\t\t\t\t\t{\n\t\t\t\t\t\t\t\"time\": 0.6333,\n\t\t\t\t\t\t\t\"offset\": 1,\n\t\t\t\t\t\t\t\"vertices\": [ 27.20717, 0, 27.20717, 0, -27.2072, 0, -27.2072 ]\n\t\t\t\t\t\t},\n\t\t\t\t\t\t{\n\t\t\t\t\t\t\t\"time\": 0.6667,\n\t\t\t\t\t\t\t\"offset\": 1,\n\t\t\t\t\t\t\t\"vertices\": [ 27.52427, 0, 27.52427, 0, -27.5243, 0, -27.5243 ]\n\t\t\t\t\t\t},\n\t\t\t\t\t\t{\n\t\t\t\t\t\t\t\"time\": 1,\n\t\t\t\t\t\t\t\"offset\": 1,\n\t\t\t\t\t\t\t\"vertices\": [ 15.58978, 0, 15.58978, -1.0E-5, -15.58978, -1.0E-5, -15.58978 ]\n\t\t\t\t\t\t},\n\t\t\t\t\t\t{ \"time\": 1.3333 },\n\t\t\t\t\t\t{\n\t\t\t\t\t\t\t\"time\": 1.7667,\n\t\t\t\t\t\t\t\"offset\": 1,\n\t\t\t\t\t\t\t\"vertices\": [ 14.27921, 1.0E-5, 14.27921, 0, -14.27916, 0, -14.27916 ]\n\t\t\t\t\t\t},\n\t\t\t\t\t\t{\n\t\t\t\t\t\t\t\"time\": 2,\n\t\t\t\t\t\t\t\"offset\": 1,\n\t\t\t\t\t\t\t\"vertices\": [ 27.57078, 0, 27.57078, 0, -27.5708, 0, -27.5708 ]\n\t\t\t\t\t\t},\n\t\t\t\t\t\t{\n\t\t\t\t\t\t\t\"time\": 2.3333,\n\t\t\t\t\t\t\t\"offset\": 1,\n\t\t\t\t\t\t\t\"vertices\": [ 37.55733, 0, 37.55733, 0, -37.55732, 0, -37.55732 ]\n\t\t\t\t\t\t},\n\t\t\t\t\t\t{ \"time\": 2.6667 }\n\t\t\t\t\t]\n\t\t\t\t}\n\t\t\t}\n\t\t}\n\t}\n}\n}","_skeletonJson":{"skeleton":{"hash":"LN+BRHYhEJJDDQu9XEu9lGJJwF4","spine":"3.6.52","width":87,"height":56.4,"images":""},"bones":[{"name":"root"},{"name":"normal/leaflet","parent":"root"}],"slots":[{"name":"normal/leaflet","bone":"normal/leaflet","attachment":"leaflet"},{"name":"normal/leaflet3","bone":"normal/leaflet","attachment":"leaflet"}],"skins":{"default":{},"normal":{"normal/leaflet":{"leaflet":{"name":"normal/leaflet","type":"mesh","uvs":[1,1,0,1,0,0,1,0],"triangles":[1,2,3,1,3,0],"vertices":[44.31,-26.02,-42.69,-26.02,-42.69,29.98,44.31,29.98],"hull":4,"edges":[0,2,2,4,4,6,0,6],"width":87,"height":56}},"normal/leaflet3":{"leaflet":{"name":"normal/leaflet","type":"mesh","uvs":[1,1,0,1,0,0,1,0],"triangles":[1,2,3,1,3,0],"vertices":[-42.69,-26.42,44.31,-26.42,44.31,29.58,-42.69,29.58],"hull":4,"edges":[0,2,2,4,4,6,0,6],"width":87,"height":56}}}},"animations":{"l1":{"slots":{"normal/leaflet":{"attachment":[{"time":0,"name":"leaflet"},{"time":0.4333,"name":"leaflet"},{"time":0.6333,"name":"leaflet"},{"time":0.6667,"name":null},{"time":1,"name":null},{"time":1.3333,"name":null},{"time":1.8,"name":null},{"time":2,"name":"leaflet"},{"time":2.3333,"name":"leaflet"},{"time":2.6667,"name":"leaflet"}]},"normal/leaflet3":{"attachment":[{"time":0,"name":null},{"time":0.4333,"name":null},{"time":0.6333,"name":null},{"time":0.6667,"name":"leaflet"},{"time":1,"name":"leaflet"},{"time":1.3333,"name":"leaflet"},{"time":1.8,"name":"leaflet"},{"time":2,"name":null},{"time":2.3333,"name":null},{"time":2.6667,"name":null}]}},"bones":{"root":{"rotate":[{"time":0,"angle":0,"curve":"stepped"},{"time":1.3333,"angle":0,"curve":"stepped"},{"time":2.6667,"angle":0}],"translate":[{"time":0,"x":0,"y":0,"curve":"stepped"},{"time":1.3333,"x":0,"y":0,"curve":"stepped"},{"time":2.6667,"x":0,"y":0}],"scale":[{"time":0,"x":1,"y":1,"curve":"stepped"},{"time":1.3333,"x":1,"y":1,"curve":"stepped"},{"time":2.6667,"x":1,"y":1}]},"normal/leaflet":{"rotate":[{"time":0,"angle":0},{"time":0.6667,"angle":-90},{"time":1.3333,"angle":180},{"time":2.6667,"angle":0}],"translate":[{"time":0,"x":0,"y":0,"curve":"stepped"},{"time":1.3333,"x":0,"y":0,"curve":"stepped"},{"time":2.6667,"x":0,"y":0}],"scale":[{"time":0,"x":1,"y":1,"curve":"stepped"},{"time":1.3333,"x":1,"y":1,"curve":"stepped"},{"time":2.6667,"x":1,"y":1}],"shear":[{"time":0,"x":0,"y":0,"curve":"stepped"},{"time":1.3333,"x":0,"y":0,"curve":"stepped"},{"time":2.6667,"x":0,"y":0}]}},"deform":{"normal":{"normal/leaflet":{"leaflet":[{"time":0},{"time":0.4333,"offset":1,"vertices":[22.57752,0,22.57752,0,-22.57752,0,-22.57752]},{"time":0.6667,"offset":1,"vertices":[27.52428,0,27.52428,0,-27.52428,0,-27.52428]},{"time":1,"curve":"stepped"},{"time":1.3333},{"time":1.8,"offset":1,"vertices":[23.71909,0,23.71909,0,-23.71909,0,-23.71909]},{"time":2,"offset":1,"vertices":[27.25158,0,27.25158,0,-27.25161,0,-27.25161]},{"time":2.3333,"offset":1,"vertices":[19.90234,0,19.90234,0,-19.90234,0,-19.90234]},{"time":2.6667}]},"normal/leaflet3":{"leaflet":[{"time":0},{"time":0.4333,"offset":1,"vertices":[25.62167,0,25.62167,0,-25.6217,0,-25.6217]},{"time":0.6333,"offset":1,"vertices":[27.20717,0,27.20717,0,-27.2072,0,-27.2072]},{"time":0.6667,"offset":1,"vertices":[27.52427,0,27.52427,0,-27.5243,0,-27.5243]},{"time":1,"offset":1,"vertices":[15.58978,0,15.58978,-0.00001,-15.58978,-0.00001,-15.58978]},{"time":1.3333},{"time":1.8,"offset":1,"vertices":[14.27921,0.00001,14.27921,0,-14.27916,0,-14.27916]},{"time":2,"offset":1,"vertices":[27.57078,0,27.57078,0,-27.5708,0,-27.5708]},{"time":2.3333,"offset":1,"vertices":[37.55733,0,37.55733,0,-37.55732,0,-37.55732]},{"time":2.6667}]}}}},"l2":{"slots":{"normal/leaflet":{"attachment":[{"time":0,"name":"leaflet"},{"time":0.4333,"name":"leaflet"},{"time":0.6333,"name":"leaflet"},{"time":0.6667,"name":null},{"time":1,"name":null},{"time":1.3333,"name":null},{"time":1.7667,"name":null},{"time":2,"name":"leaflet"},{"time":2.3333,"name":"leaflet"},{"time":2.6667,"name":"leaflet"}]},"normal/leaflet3":{"attachment":[{"time":0,"name":null},{"time":0.4333,"name":null},{"time":0.6333,"name":null},{"time":0.6667,"name":"leaflet"},{"time":1,"name":"leaflet"},{"time":1.3333,"name":"leaflet"},{"time":1.7667,"name":"leaflet"},{"time":2,"name":null},{"time":2.3333,"name":null},{"time":2.6667,"name":null}]}},"bones":{"root":{"rotate":[{"time":0,"angle":0,"curve":"stepped"},{"time":1.3333,"angle":0,"curve":"stepped"},{"time":2.6667,"angle":0}],"translate":[{"time":0,"x":0,"y":0,"curve":"stepped"},{"time":1.3333,"x":0,"y":0,"curve":"stepped"},{"time":2.6667,"x":0,"y":0}],"scale":[{"time":0,"x":1,"y":1,"curve":"stepped"},{"time":1.3333,"x":1,"y":1,"curve":"stepped"},{"time":2.6667,"x":1,"y":1}]},"normal/leaflet":{"rotate":[{"time":0,"angle":-90},{"time":0.6667,"angle":180},{"time":1.3333,"angle":90},{"time":2.6667,"angle":-90}],"translate":[{"time":0,"x":0,"y":0,"curve":"stepped"},{"time":1.3333,"x":0,"y":0,"curve":"stepped"},{"time":2.6667,"x":0,"y":0}],"scale":[{"time":0,"x":1,"y":1,"curve":"stepped"},{"time":1.3333,"x":1,"y":1,"curve":"stepped"},{"time":2.6667,"x":1,"y":1}],"shear":[{"time":0,"x":0,"y":0,"curve":"stepped"},{"time":1.3333,"x":0,"y":0,"curve":"stepped"},{"time":2.6667,"x":0,"y":0}]}},"deform":{"normal":{"normal/leaflet":{"leaflet":[{"time":0},{"time":0.4333,"offset":1,"vertices":[22.57752,0,22.57752,0,-22.57752,0,-22.57752]},{"time":0.6667,"offset":1,"vertices":[27.52428,0,27.52428,0,-27.52428,0,-27.52428]},{"time":1,"curve":"stepped"},{"time":1.3333},{"time":1.7667,"offset":1,"vertices":[23.71909,0,23.71909,0,-23.71909,0,-23.71909]},{"time":2,"offset":1,"vertices":[27.25158,0,27.25158,0,-27.25161,0,-27.25161]},{"time":2.3333,"offset":1,"vertices":[19.90234,0,19.90234,0,-19.90234,0,-19.90234]},{"time":2.6667}]},"normal/leaflet3":{"leaflet":[{"time":0},{"time":0.4333,"offset":1,"vertices":[25.62167,0,25.62167,0,-25.6217,0,-25.6217]},{"time":0.6333,"offset":1,"vertices":[27.20717,0,27.20717,0,-27.2072,0,-27.2072]},{"time":0.6667,"offset":1,"vertices":[27.52427,0,27.52427,0,-27.5243,0,-27.5243]},{"time":1,"offset":1,"vertices":[15.58978,0,15.58978,-0.00001,-15.58978,-0.00001,-15.58978]},{"time":1.3333},{"time":1.7667,"offset":1,"vertices":[14.27921,0.00001,14.27921,0,-14.27916,0,-14.27916]},{"time":2,"offset":1,"vertices":[27.57078,0,27.57078,0,-27.5708,0,-27.5708]},{"time":2.3333,"offset":1,"vertices":[37.55733,0,37.55733,0,-37.55732,0,-37.55732]},{"time":2.6667}]}}}}}},"_atlasText":"\nleaflet.png\nsize: 128,64\nformat: RGBA8888\nfilter: Linear,Linear\nrepeat: none\nnormal/leaflet\n  rotate: false\n  xy: 2, 2\n  size: 87, 56\n  orig: 87, 56\n  offset: 0, 0\n  index: -1\n","textures":[{"__uuid__":"08a87Kg0BLtqL/wdnWcrVI"}],"textureNames":["leaflet.png"]}